{
  "app:toggle-right-sidebar": [
    {
      "modifiers": [
        "Alt",
        "Ctrl",
        "Mod",
        "Shift"
      ],
      "key": "]"
    }
  ],
  "app:toggle-left-sidebar": [
    {
      "modifiers": [
        "Alt",
        "Ctrl",
        "Mod",
        "Shift"
      ],
      "key": "["
    }
  ],
  "editor:set-heading-1": [
    {
      "modifiers": [
        "Alt",
        "Ctrl",
        "Mod",
        "Shift"
      ],
      "key": "1"
    }
  ],
  "editor:set-heading-2": [
    {
      "modifiers": [
        "Alt",
        "Ctrl",
        "Mod",
        "Shift"
      ],
      "key": "2"
    }
  ],
  "editor:set-heading-3": [
    {
      "modifiers": [
        "Alt",
        "Ctrl",
        "Mod",
        "Shift"
      ],
      "key": "3"
    }
  ],
  "editor:set-heading-4": [
    {
      "modifiers": [
        "Alt",
        "Ctrl",
        "Mod",
        "Shift"
      ],
      "key": "4"
    }
  ],
  "editor:set-heading-5": [
    {
      "modifiers": [
        "Alt",
        "Ctrl",
        "Mod",
        "Shift"
      ],
      "key": "5"
    }
  ],
  "editor:set-heading-6": [
    {
      "modifiers": [
        "Alt",
        "Ctrl",
        "Mod",
        "Shift"
      ],
      "key": "6"
    }
  ],
  "insert-current-date": [
    {
      "modifiers": [
        "Alt",
        "Ctrl",
        "Mod",
        "Shift"
      ],
      "key": "D"
    }
  ],
  "make-md:mk-blink": [],
  "terminal:open-terminal.integrated.root": [
    {
      "modifiers": [
        "Mod"
      ],
      "key": "J"
    }
  ]
}